hello.py
adsk_amp-0.0.1.dist-info/METADATA
adsk_amp-0.0.1.dist-info/WHEEL
adsk_amp-0.0.1.dist-info/top_level.txt
adsk_amp-0.0.1.dist-info/RECORD
