Metadata-Version: 2.1
Name: adsk-amp
Version: 0.0.1
Summary: amp package
Requires-Python: >=3.11
